AUTHORS.rst
CONTRIBUTING.rst
HISTORY.rst
LICENSE
MANIFEST.in
README.rst
setup.cfg
setup.py
docs/Makefile
docs/authors.rst
docs/cli.rst
docs/code.rst
docs/conf.py
docs/contributing.rst
docs/history.rst
docs/index.rst
docs/installation.rst
docs/make.bat
docs/readme.rst
docs/usage.rst
docs/_build/_static/ajax-loader.gif
docs/_build/_static/comment-bright.png
docs/_build/_static/comment-close.png
docs/_build/_static/comment.png
docs/_build/_static/down-pressed.png
docs/_build/_static/down.png
docs/_build/_static/file.png
docs/_build/_static/minus.png
docs/_build/_static/plus.png
docs/_build/_static/up-pressed.png
docs/_build/_static/up.png
docs/_build/html/_static/ajax-loader.gif
docs/_build/html/_static/comment-bright.png
docs/_build/html/_static/comment-close.png
docs/_build/html/_static/comment.png
docs/_build/html/_static/down-pressed.png
docs/_build/html/_static/down.png
docs/_build/html/_static/file.png
docs/_build/html/_static/minus.png
docs/_build/html/_static/plus.png
docs/_build/html/_static/up-pressed.png
docs/_build/html/_static/up.png
gdal_build_debug/__init__.py
gdal_build_debug/cli.py
gdal_build_debug/cli_test_fns.py
gdal_build_debug/config_test_fns.py
gdal_build_debug/foo.py
gdal_build_debug.egg-info/PKG-INFO
gdal_build_debug.egg-info/SOURCES.txt
gdal_build_debug.egg-info/dependency_links.txt
gdal_build_debug.egg-info/entry_points.txt
gdal_build_debug.egg-info/not-zip-safe
gdal_build_debug.egg-info/requires.txt
gdal_build_debug.egg-info/top_level.txt
tests/__init__.py
tests/test_cli_integration.py
tests/test_config_processing.py
tests/fixtures/__init__.py
tests/fixtures/configure.log
tests/fixtures/line_endings_that_should_fail.py
tests/fixtures/line_endings_that_should_pass.py
tests/fixtures/make.log