Metadata-Version: 1.1
Name: gdal-build-debug
Version: 0.1.0
Summary: A suite of tests of whether gdal configured/built with the packages and    formats you wanted
Home-page: https://github.com/skalt/gdal_build_debug
Author: Steven Kalt
Author-email: kalt.steven@gmail.com
License: MIT license
Keywords: gdal,ogr,GIS,tests
Platform: UNKNOWN
Classifier: Development Status :: 2 - Pre-Alpha
Classifier: Intended Audience :: Developers
Classifier: License :: OSI Approved :: MIT License
Classifier: Natural Language :: English
Classifier: Programming Language :: Python :: 2
Classifier: Programming Language :: Python :: 2.6
Classifier: Programming Language :: Python :: 2.7
Classifier: Programming Language :: Python :: 3
Classifier: Programming Language :: Python :: 3.3
Classifier: Programming Language :: Python :: 3.4
Classifier: Programming Language :: Python :: 3.5
